[
  {
    "route": "/compound-interest",
    "firstLoadUncompressedJsBytes": 533373,
    "firstLoadChunkPaths": [
      ".next\\static\\chunks\\08z1sc_1.vb0c.js",
      ".next\\static\\chunks\\0d3shmwh5_nmn.js",
      ".next\\static\\chunks\\0t3y_593mzk-1.js",
      ".next\\static\\chunks\\15xrurgzs99gv.js",
      ".next\\static\\chunks\\0dgq26a5_oy.a.js",
      ".next\\static\\chunks\\0mstyq17cbf8-.js",
      ".next\\static\\chunks\\0oqwp2.ok_yzn.js",
      ".next\\static\\chunks\\turbopack-0b2-7jklwwqbb.js"
    ]
  },
  {
    "route": "/resize-image",
    "firstLoadUncompressedJsBytes": 533370,
    "firstLoadChunkPaths": [
      ".next\\static\\chunks\\08z1sc_1.vb0c.js",
      ".next\\static\\chunks\\0d3shmwh5_nmn.js",
      ".next\\static\\chunks\\0.wzx41frbakf.js",
      ".next\\static\\chunks\\15xrurgzs99gv.js",
      ".next\\static\\chunks\\0dgq26a5_oy.a.js",
      ".next\\static\\chunks\\0mstyq17cbf8-.js",
      ".next\\static\\chunks\\0oqwp2.ok_yzn.js",
      ".next\\static\\chunks\\turbopack-0b2-7jklwwqbb.js"
    ]
  },
  {
    "route": "/remove-bg",
    "firstLoadUncompressedJsBytes": 532493,
    "firstLoadChunkPaths": [
      ".next\\static\\chunks\\08z1sc_1.vb0c.js",
      ".next\\static\\chunks\\0d3shmwh5_nmn.js",
      ".next\\static\\chunks\\09ppuwprprwbw.js",
      ".next\\static\\chunks\\15xrurgzs99gv.js",
      ".next\\static\\chunks\\0dgq26a5_oy.a.js",
      ".next\\static\\chunks\\0mstyq17cbf8-.js",
      ".next\\static\\chunks\\0oqwp2.ok_yzn.js",
      ".next\\static\\chunks\\turbopack-0b2-7jklwwqbb.js"
    ]
  },
  {
    "route": "/convert-image",
    "firstLoadUncompressedJsBytes": 532482,
    "firstLoadChunkPaths": [
      ".next\\static\\chunks\\08z1sc_1.vb0c.js",
      ".next\\static\\chunks\\0d3shmwh5_nmn.js",
      ".next\\static\\chunks\\0lskidny-a1il.js",
      ".next\\static\\chunks\\15xrurgzs99gv.js",
      ".next\\static\\chunks\\0dgq26a5_oy.a.js",
      ".next\\static\\chunks\\0mstyq17cbf8-.js",
      ".next\\static\\chunks\\0oqwp2.ok_yzn.js",
      ".next\\static\\chunks\\turbopack-0b2-7jklwwqbb.js"
    ]
  },
  {
    "route": "/emi-calculator",
    "firstLoadUncompressedJsBytes": 532419,
    "firstLoadChunkPaths": [
      ".next\\static\\chunks\\08z1sc_1.vb0c.js",
      ".next\\static\\chunks\\0d3shmwh5_nmn.js",
      ".next\\static\\chunks\\0dn-8gdyhgu1k.js",
      ".next\\static\\chunks\\15xrurgzs99gv.js",
      ".next\\static\\chunks\\0dgq26a5_oy.a.js",
      ".next\\static\\chunks\\0mstyq17cbf8-.js",
      ".next\\static\\chunks\\0oqwp2.ok_yzn.js",
      ".next\\static\\chunks\\turbopack-0b2-7jklwwqbb.js"
    ]
  },
  {
    "route": "/compress-image",
    "firstLoadUncompressedJsBytes": 531858,
    "firstLoadChunkPaths": [
      ".next\\static\\chunks\\08z1sc_1.vb0c.js",
      ".next\\static\\chunks\\0d3shmwh5_nmn.js",
      ".next\\static\\chunks\\0gdsf~sb6bvkk.js",
      ".next\\static\\chunks\\15xrurgzs99gv.js",
      ".next\\static\\chunks\\0dgq26a5_oy.a.js",
      ".next\\static\\chunks\\0mstyq17cbf8-.js",
      ".next\\static\\chunks\\0oqwp2.ok_yzn.js",
      ".next\\static\\chunks\\turbopack-0b2-7jklwwqbb.js"
    ]
  },
  {
    "route": "/bmi-calculator",
    "firstLoadUncompressedJsBytes": 531289,
    "firstLoadChunkPaths": [
      ".next\\static\\chunks\\08z1sc_1.vb0c.js",
      ".next\\static\\chunks\\0d3shmwh5_nmn.js",
      ".next\\static\\chunks\\0sstnx8b75cys.js",
      ".next\\static\\chunks\\15xrurgzs99gv.js",
      ".next\\static\\chunks\\0dgq26a5_oy.a.js",
      ".next\\static\\chunks\\0mstyq17cbf8-.js",
      ".next\\static\\chunks\\0oqwp2.ok_yzn.js",
      ".next\\static\\chunks\\turbopack-0b2-7jklwwqbb.js"
    ]
  },
  {
    "route": "/percentage-calculator",
    "firstLoadUncompressedJsBytes": 530123,
    "firstLoadChunkPaths": [
      ".next\\static\\chunks\\08z1sc_1.vb0c.js",
      ".next\\static\\chunks\\0d3shmwh5_nmn.js",
      ".next\\static\\chunks\\12p05o-66qh5m.js",
      ".next\\static\\chunks\\15xrurgzs99gv.js",
      ".next\\static\\chunks\\0dgq26a5_oy.a.js",
      ".next\\static\\chunks\\0mstyq17cbf8-.js",
      ".next\\static\\chunks\\0oqwp2.ok_yzn.js",
      ".next\\static\\chunks\\turbopack-0b2-7jklwwqbb.js"
    ]
  },
  {
    "route": "/age-calculator",
    "firstLoadUncompressedJsBytes": 530007,
    "firstLoadChunkPaths": [
      ".next\\static\\chunks\\08z1sc_1.vb0c.js",
      ".next\\static\\chunks\\0d3shmwh5_nmn.js",
      ".next\\static\\chunks\\15a_xa6xkc5t4.js",
      ".next\\static\\chunks\\15xrurgzs99gv.js",
      ".next\\static\\chunks\\0dgq26a5_oy.a.js",
      ".next\\static\\chunks\\0mstyq17cbf8-.js",
      ".next\\static\\chunks\\0oqwp2.ok_yzn.js",
      ".next\\static\\chunks\\turbopack-0b2-7jklwwqbb.js"
    ]
  },
  {
    "route": "/",
    "firstLoadUncompressedJsBytes": 524497,
    "firstLoadChunkPaths": [
      ".next\\static\\chunks\\08z1sc_1.vb0c.js",
      ".next\\static\\chunks\\0d3shmwh5_nmn.js",
      ".next\\static\\chunks\\15xrurgzs99gv.js",
      ".next\\static\\chunks\\0dgq26a5_oy.a.js",
      ".next\\static\\chunks\\0mstyq17cbf8-.js",
      ".next\\static\\chunks\\0oqwp2.ok_yzn.js",
      ".next\\static\\chunks\\turbopack-0b2-7jklwwqbb.js"
    ]
  },
  {
    "route": "/_not-found",
    "firstLoadUncompressedJsBytes": 524497,
    "firstLoadChunkPaths": [
      ".next\\static\\chunks\\08z1sc_1.vb0c.js",
      ".next\\static\\chunks\\0d3shmwh5_nmn.js",
      ".next\\static\\chunks\\15xrurgzs99gv.js",
      ".next\\static\\chunks\\0dgq26a5_oy.a.js",
      ".next\\static\\chunks\\0mstyq17cbf8-.js",
      ".next\\static\\chunks\\0oqwp2.ok_yzn.js",
      ".next\\static\\chunks\\turbopack-0b2-7jklwwqbb.js"
    ]
  }
]